deduplicator.py
deduplicator-1.0.0.dist-info/DESCRIPTION.rst
deduplicator-1.0.0.dist-info/METADATA
deduplicator-1.0.0.dist-info/RECORD
deduplicator-1.0.0.dist-info/WHEEL
deduplicator-1.0.0.dist-info/entry_points.txt
deduplicator-1.0.0.dist-info/metadata.json
deduplicator-1.0.0.dist-info/top_level.txt
