Metadata-Version: 2.0
Name: deduplicator
Version: 1.0.0
Summary: Rapid file deduplication utility for Unix systems
Home-page: https://github.com/sevangelatos/Deduplicator
Author: Spiros Evangelatos
Author-email: UNKNOWN
License: UNKNOWN
Keywords: deduplication hardlinks backup duplicates
Platform: UNKNOWN
Classifier: Development Status :: 5 - Production/Stable
Classifier: Intended Audience :: System Administrators
Classifier: Topic :: System :: Systems Administration
Classifier: License :: OSI Approved :: BSD License
Classifier: Programming Language :: Python :: 2
Classifier: Programming Language :: Python :: 2.7
Classifier: Programming Language :: Python :: 3
Classifier: Programming Language :: Python :: 3.4
Classifier: Programming Language :: Python :: 3.5
Classifier: Programming Language :: Python :: 3.6
